{
  "latest_month": "May 2026",
  "previous_month": "April 2026",
  "headline_yoy": 4.2,
  "headline_mom": 0.5,
  "prev_headline_yoy": 3.8,
  "prev_headline_mom": 0.6,
  "core_yoy": 2.8,
  "core_mom": 0.2,
  "prev_core_yoy": 2.7,
  "prev_core_mom": 0.4,
  "energy_yoy": 23.0,
  "energy_mom": 3.9,
  "prev_energy_yoy": 17.5,
  "prev_energy_mom": 3.8,
  "gasoline_yoy": 40.5,
  "gasoline_mom": 7.0,
  "prev_gasoline_yoy": 28.4,
  "prev_gasoline_mom": 5.4,
  "shelter_yoy": 3.4,
  "shelter_mom": 0.3,
  "prev_shelter_yoy": 3.3,
  "prev_shelter_mom": 0.6,
  "food_yoy": 3.0,
  "food_mom": 0.2,
  "prev_food_yoy": 3.1,
  "prev_food_mom": 0.5,
  "core_goods_yoy": 1.1,
  "core_goods_mom": -0.1,
  "prev_core_goods_yoy": 1.1,
  "prev_core_goods_mom": 0.0,
  "core_services_yoy": 3.4,
  "core_services_mom": 0.3,
  "prev_core_services_yoy": 3.3,
  "prev_core_services_mom": 0.5,
  "headline_core_gap": 1.3,
  "contrib_energy_pp": 1.49,
  "contrib_shelter_pp": 1.22,
  "contrib_food_pp": 0.43,
  "contrib_core_goods_pp": 0.2,
  "contrib_residual_pp": 0.83,
  "energy_contribution_share": 36,
  "weights": {
    "energy": 6.5,
    "shelter": 36.4,
    "food": 14.3,
    "core_goods": 18.5
  },
  "energy_peak_2008": 29.3,
  "energy_peak_2008_month": "July 2008",
  "gap_peak_2008": 3.0,
  "energy_peak_2022": 41.5,
  "energy_peak_2022_month": "June 2022",
  "gap_peak_2022": 3.1,
  "energy_peak_current": 23.0,
  "energy_peak_current_month": "May 2026",
  "gap_peak_current": 1.3,
  "wti_latest": 95.0,
  "wti_latest_date": "June 08, 2026",
  "wti_peak_2026": 114.6,
  "wti_peak_2026_date": "April 07, 2026",
  "wti_jan_2026_avg": 60.0,
  "wti_peak_pct_vs_jan": 90.8,
  "days_above_100": 24,
  "gas_retail_latest": 4.15,
  "gas_retail_latest_date": "June 08, 2026",
  "gas_retail_jan_2026_avg": 2.81,
  "gas_retail_pct_vs_jan": 47.6,
  "labor_month": "May 2026",
  "payroll_latest": 172,
  "payroll_3mo_avg": 188,
  "unrate_latest": 4.3,
  "ahe_yoy": 3.4,
  "ahe_mom": 0.3,
  "real_ahe_yoy": -0.7,
  "prev_real_ahe_yoy": -0.2,
  "neg_real_wage_months_12m": 2,
  "dgs2_latest": 4.13,
  "dgs10_latest": 4.53,
  "spread_latest_bps": 40,
  "rates_latest_date": "June 09, 2026",
  "target_lower": 3.5,
  "target_upper": 3.75,
  "target_range": "3.50-3.75",
  "target_midpoint": 3.62,
  "dot_median_eoy2026": 3.375,
  "dot_median_eoy2027": 3.125,
  "dot_median_eoy2028": 3.125,
  "dot_iqr_lo_2026": 3.125,
  "dot_iqr_hi_2026": 3.625,
  "market_implied_eoy2026": 3.55,
  "market_implied_eoy2027": 3.3,
  "june_hold_prob_pct": 93,
  "release_date": "June 10, 2026",
  "next_cpi_release": "July 14, 2026",
  "fomc_window": "June 16-17, 2026",
  "data_current_as_of": "May 2026 CPI (BLS release: June 10, 2026); market data through June 08, 2026",
  "source_url": "https://www.bls.gov/news.release/cpi.htm"
}